{
  "stats": {
    "initial_balance": 10000.0,
    "final_balance": 9129.48,
    "net_profit": -870.52,
    "total_return_pct": -8.71,
    "total_trades": 92,
    "winning_trades": 32,
    "losing_trades": 60,
    "win_rate": 34.78,
    "max_drawdown": 10.13,
    "sharpe_ratio": -1.92,
    "profit_factor": 0.59,
    "gross_profit": 1231.05,
    "gross_loss": 2101.57,
    "avg_profit": 1.11,
    "avg_loss": 0.94,
    "average_win_abs": 38.47,
    "average_loss_abs": 35.03,
    "payoff_ratio": 1.1,
    "expectancy_pct": -0.22,
    "regime_breakdown": [
      {
        "regime": "trend_bull",
        "total_trades": 63,
        "win_rate": 36.51,
        "profit_factor": 0.62,
        "net_profit": -544.32,
        "total_result_pct": -12.17,
        "avg_result_pct": -0.19,
        "winning_trades": 23,
        "losing_trades": 40,
        "avg_mfe_pct": 0.84,
        "avg_mae_pct": 0.55
      },
      {
        "regime": "trend_bear",
        "total_trades": 29,
        "win_rate": 31.03,
        "profit_factor": 0.52,
        "net_profit": -326.21,
        "total_result_pct": -8.48,
        "avg_result_pct": -0.29,
        "winning_trades": 9,
        "losing_trades": 20,
        "avg_mfe_pct": 0.83,
        "avg_mae_pct": 0.68
      }
    ],
    "setup_type_breakdown": [
      {
        "setup_type": "ema_rsi_resume_long",
        "total_trades": 63,
        "win_rate": 36.51,
        "profit_factor": 0.62,
        "net_profit": -544.32,
        "total_result_pct": -12.17,
        "avg_result_pct": -0.19,
        "winning_trades": 23,
        "losing_trades": 40,
        "avg_mfe_pct": 0.84,
        "avg_mae_pct": 0.55
      },
      {
        "setup_type": "ema_rsi_resume_short",
        "total_trades": 29,
        "win_rate": 31.03,
        "profit_factor": 0.52,
        "net_profit": -326.21,
        "total_result_pct": -8.48,
        "avg_result_pct": -0.29,
        "winning_trades": 9,
        "losing_trades": 20,
        "avg_mfe_pct": 0.83,
        "avg_mae_pct": 0.68
      }
    ],
    "market_state_breakdown": [
      {
        "market_state": "ema_rsi_resume_bull",
        "total_trades": 63,
        "win_rate": 36.51,
        "profit_factor": 0.62,
        "net_profit": -544.32,
        "total_result_pct": -12.17,
        "avg_result_pct": -0.19,
        "winning_trades": 23,
        "losing_trades": 40,
        "avg_mfe_pct": 0.84,
        "avg_mae_pct": 0.55
      },
      {
        "market_state": "ema_rsi_resume_bear",
        "total_trades": 29,
        "win_rate": 31.03,
        "profit_factor": 0.52,
        "net_profit": -326.21,
        "total_result_pct": -8.48,
        "avg_result_pct": -0.29,
        "winning_trades": 9,
        "losing_trades": 20,
        "avg_mfe_pct": 0.83,
        "avg_mae_pct": 0.68
      }
    ],
    "execution_mode_breakdown": [
      {
        "execution_mode": "ema_rsi_resume",
        "total_trades": 92,
        "win_rate": 34.78,
        "profit_factor": 0.59,
        "net_profit": -870.52,
        "total_result_pct": -20.65,
        "avg_result_pct": -0.22,
        "winning_trades": 32,
        "losing_trades": 60,
        "avg_mfe_pct": 0.84,
        "avg_mae_pct": 0.59
      }
    ],
    "exit_reason_counts": {
      "STOP_LOSS": 44,
      "TRAILING_STOP": 30,
      "TAKE_PROFIT": 18
    },
    "exit_type_breakdown": [
      {
        "exit_reason": "STOP_LOSS",
        "total_trades": 44,
        "win_rate": 0.0,
        "profit_factor": 0.0,
        "net_profit": -1900.96,
        "total_result_pct": -51.74,
        "avg_result_pct": -1.18,
        "winning_trades": 0,
        "losing_trades": 44,
        "avg_mfe_pct": 0.2,
        "avg_mae_pct": 0.93
      },
      {
        "exit_reason": "TRAILING_STOP",
        "total_trades": 30,
        "win_rate": 46.67,
        "profit_factor": 0.63,
        "net_profit": -74.07,
        "total_result_pct": -0.53,
        "avg_result_pct": -0.02,
        "winning_trades": 14,
        "losing_trades": 16,
        "avg_mfe_pct": 1.07,
        "avg_mae_pct": 0.33
      },
      {
        "exit_reason": "TAKE_PROFIT",
        "total_trades": 18,
        "win_rate": 100.0,
        "profit_factor": 1104.51,
        "net_profit": 1104.51,
        "total_result_pct": 31.62,
        "avg_result_pct": 1.76,
        "winning_trades": 18,
        "losing_trades": 0,
        "avg_mfe_pct": 2.01,
        "avg_mae_pct": 0.21
      }
    ],
    "entry_quality_breakdown": [
      {
        "entry_quality": "strong",
        "total_trades": 86,
        "win_rate": 34.88,
        "profit_factor": 0.54,
        "net_profit": -889.74,
        "total_result_pct": -20.95,
        "avg_result_pct": -0.24,
        "winning_trades": 30,
        "losing_trades": 56,
        "avg_mfe_pct": 0.83,
        "avg_mae_pct": 0.59
      },
      {
        "entry_quality": "acceptable",
        "total_trades": 6,
        "win_rate": 33.33,
        "profit_factor": 1.13,
        "net_profit": 19.21,
        "total_result_pct": 0.3,
        "avg_result_pct": 0.05,
        "winning_trades": 2,
        "losing_trades": 4,
        "avg_mfe_pct": 0.91,
        "avg_mae_pct": 0.62
      }
    ],
    "risk_mode_breakdown": [
      {
        "risk_mode": "reduced",
        "total_trades": 71,
        "win_rate": 38.03,
        "profit_factor": 0.71,
        "net_profit": -364.45,
        "total_result_pct": -12.45,
        "avg_result_pct": -0.18,
        "winning_trades": 27,
        "losing_trades": 44,
        "avg_mfe_pct": 0.87,
        "avg_mae_pct": 0.58
      },
      {
        "risk_mode": "normal",
        "total_trades": 21,
        "win_rate": 23.81,
        "profit_factor": 0.4,
        "net_profit": -506.07,
        "total_result_pct": -8.2,
        "avg_result_pct": -0.39,
        "winning_trades": 5,
        "losing_trades": 16,
        "avg_mfe_pct": 0.73,
        "avg_mae_pct": 0.61
      }
    ],
    "break_even_activated_count": 0,
    "trailing_activated_count": 48,
    "post_pump_protection_count": 0,
    "structure_exit_count": 0,
    "regime_exit_count": 0,
    "avg_mfe_pct": 0.84,
    "avg_mae_pct": 0.59,
    "avg_rr_realized": -0.28,
    "avg_profit_given_back_pct": 1.06,
    "max_consecutive_wins": 4,
    "max_consecutive_losses": 10,
    "hour_of_day_breakdown": [
      {
        "hour_of_day": 14,
        "total_trades": 8,
        "win_rate": 25.0,
        "profit_factor": 0.63,
        "net_profit": -58.36,
        "total_result_pct": -0.72,
        "avg_result_pct": -0.09,
        "winning_trades": 2,
        "losing_trades": 6,
        "avg_mfe_pct": 0.93,
        "avg_mae_pct": 0.49
      },
      {
        "hour_of_day": 16,
        "total_trades": 7,
        "win_rate": 42.86,
        "profit_factor": 0.76,
        "net_profit": -20.97,
        "total_result_pct": -0.93,
        "avg_result_pct": -0.13,
        "winning_trades": 3,
        "losing_trades": 4,
        "avg_mfe_pct": 1.06,
        "avg_mae_pct": 0.53
      },
      {
        "hour_of_day": 19,
        "total_trades": 7,
        "win_rate": 57.14,
        "profit_factor": 1.58,
        "net_profit": 60.55,
        "total_result_pct": 2.13,
        "avg_result_pct": 0.3,
        "winning_trades": 4,
        "losing_trades": 3,
        "avg_mfe_pct": 1.13,
        "avg_mae_pct": 0.49
      },
      {
        "hour_of_day": 8,
        "total_trades": 6,
        "win_rate": 0.0,
        "profit_factor": 0.0,
        "net_profit": -228.02,
        "total_result_pct": -5.89,
        "avg_result_pct": -0.98,
        "winning_trades": 0,
        "losing_trades": 6,
        "avg_mfe_pct": 0.27,
        "avg_mae_pct": 0.82
      },
      {
        "hour_of_day": 9,
        "total_trades": 6,
        "win_rate": 50.0,
        "profit_factor": 0.32,
        "net_profit": -67.3,
        "total_result_pct": -2.33,
        "avg_result_pct": -0.39,
        "winning_trades": 3,
        "losing_trades": 3,
        "avg_mfe_pct": 0.81,
        "avg_mae_pct": 0.59
      },
      {
        "hour_of_day": 13,
        "total_trades": 6,
        "win_rate": 16.67,
        "profit_factor": 0.02,
        "net_profit": -145.43,
        "total_result_pct": -4.71,
        "avg_result_pct": -0.79,
        "winning_trades": 1,
        "losing_trades": 5,
        "avg_mfe_pct": 0.41,
        "avg_mae_pct": 0.76
      },
      {
        "hour_of_day": 21,
        "total_trades": 6,
        "win_rate": 0.0,
        "profit_factor": 0.0,
        "net_profit": -228.44,
        "total_result_pct": -5.98,
        "avg_result_pct": -1.0,
        "winning_trades": 0,
        "losing_trades": 6,
        "avg_mfe_pct": 0.22,
        "avg_mae_pct": 0.75
      },
      {
        "hour_of_day": 1,
        "total_trades": 5,
        "win_rate": 20.0,
        "profit_factor": 0.2,
        "net_profit": -187.36,
        "total_result_pct": -2.2,
        "avg_result_pct": -0.44,
        "winning_trades": 1,
        "losing_trades": 4,
        "avg_mfe_pct": 0.74,
        "avg_mae_pct": 0.6
      },
      {
        "hour_of_day": 20,
        "total_trades": 5,
        "win_rate": 60.0,
        "profit_factor": 1.68,
        "net_profit": 45.86,
        "total_result_pct": 1.59,
        "avg_result_pct": 0.32,
        "winning_trades": 3,
        "losing_trades": 2,
        "avg_mfe_pct": 1.29,
        "avg_mae_pct": 0.51
      },
      {
        "hour_of_day": 0,
        "total_trades": 4,
        "win_rate": 75.0,
        "profit_factor": 1.75,
        "net_profit": 59.03,
        "total_result_pct": 1.44,
        "avg_result_pct": 0.36,
        "winning_trades": 3,
        "losing_trades": 1,
        "avg_mfe_pct": 1.27,
        "avg_mae_pct": 0.49
      },
      {
        "hour_of_day": 2,
        "total_trades": 4,
        "win_rate": 25.0,
        "profit_factor": 0.08,
        "net_profit": -58.1,
        "total_result_pct": -1.99,
        "avg_result_pct": -0.5,
        "winning_trades": 1,
        "losing_trades": 3,
        "avg_mfe_pct": 0.74,
        "avg_mae_pct": 0.66
      },
      {
        "hour_of_day": 12,
        "total_trades": 4,
        "win_rate": 25.0,
        "profit_factor": 0.43,
        "net_profit": -79.32,
        "total_result_pct": -1.46,
        "avg_result_pct": -0.37,
        "winning_trades": 1,
        "losing_trades": 3,
        "avg_mfe_pct": 0.72,
        "avg_mae_pct": 0.73
      },
      {
        "hour_of_day": 18,
        "total_trades": 4,
        "win_rate": 25.0,
        "profit_factor": 0.63,
        "net_profit": -31.03,
        "total_result_pct": -0.68,
        "avg_result_pct": -0.17,
        "winning_trades": 1,
        "losing_trades": 3,
        "avg_mfe_pct": 0.8,
        "avg_mae_pct": 0.55
      },
      {
        "hour_of_day": 4,
        "total_trades": 3,
        "win_rate": 33.33,
        "profit_factor": 0.67,
        "net_profit": -24.13,
        "total_result_pct": -0.9,
        "avg_result_pct": -0.3,
        "winning_trades": 1,
        "losing_trades": 2,
        "avg_mfe_pct": 0.8,
        "avg_mae_pct": 0.78
      },
      {
        "hour_of_day": 3,
        "total_trades": 2,
        "win_rate": 100.0,
        "profit_factor": 14.88,
        "net_profit": 14.88,
        "total_result_pct": 0.5,
        "avg_result_pct": 0.25,
        "winning_trades": 2,
        "losing_trades": 0,
        "avg_mfe_pct": 1.24,
        "avg_mae_pct": 0.21
      },
      {
        "hour_of_day": 5,
        "total_trades": 2,
        "win_rate": 0.0,
        "profit_factor": 0.0,
        "net_profit": -75.98,
        "total_result_pct": -2.59,
        "avg_result_pct": -1.29,
        "winning_trades": 0,
        "losing_trades": 2,
        "avg_mfe_pct": 0.02,
        "avg_mae_pct": 1.04
      },
      {
        "hour_of_day": 7,
        "total_trades": 2,
        "win_rate": 50.0,
        "profit_factor": 1.44,
        "net_profit": 31.18,
        "total_result_pct": 0.5,
        "avg_result_pct": 0.25,
        "winning_trades": 1,
        "losing_trades": 1,
        "avg_mfe_pct": 1.22,
        "avg_mae_pct": 0.49
      },
      {
        "hour_of_day": 10,
        "total_trades": 2,
        "win_rate": 50.0,
        "profit_factor": 1.46,
        "net_profit": 3.33,
        "total_result_pct": 0.1,
        "avg_result_pct": 0.05,
        "winning_trades": 1,
        "losing_trades": 1,
        "avg_mfe_pct": 1.09,
        "avg_mae_pct": 0.34
      },
      {
        "hour_of_day": 15,
        "total_trades": 2,
        "win_rate": 50.0,
        "profit_factor": 1.74,
        "net_profit": 24.51,
        "total_result_pct": 0.84,
        "avg_result_pct": 0.42,
        "winning_trades": 1,
        "losing_trades": 1,
        "avg_mfe_pct": 1.16,
        "avg_mae_pct": 0.42
      },
      {
        "hour_of_day": 17,
        "total_trades": 2,
        "win_rate": 0.0,
        "profit_factor": 0.0,
        "net_profit": -19.94,
        "total_result_pct": -0.46,
        "avg_result_pct": -0.23,
        "winning_trades": 0,
        "losing_trades": 2,
        "avg_mfe_pct": 0.79,
        "avg_mae_pct": 0.18
      },
      {
        "hour_of_day": 22,
        "total_trades": 2,
        "win_rate": 50.0,
        "profit_factor": 1.31,
        "net_profit": 10.79,
        "total_result_pct": 0.38,
        "avg_result_pct": 0.19,
        "winning_trades": 1,
        "losing_trades": 1,
        "avg_mfe_pct": 0.91,
        "avg_mae_pct": 0.67
      },
      {
        "hour_of_day": 6,
        "total_trades": 1,
        "win_rate": 100.0,
        "profit_factor": 103.22,
        "net_profit": 103.22,
        "total_result_pct": 1.65,
        "avg_result_pct": 1.65,
        "winning_trades": 1,
        "losing_trades": 0,
        "avg_mfe_pct": 1.9,
        "avg_mae_pct": 0.29
      },
      {
        "hour_of_day": 11,
        "total_trades": 1,
        "win_rate": 0.0,
        "profit_factor": 0.0,
        "net_profit": -67.97,
        "total_result_pct": -1.13,
        "avg_result_pct": -1.13,
        "winning_trades": 0,
        "losing_trades": 1,
        "avg_mfe_pct": 0.0,
        "avg_mae_pct": 0.88
      },
      {
        "hour_of_day": 23,
        "total_trades": 1,
        "win_rate": 100.0,
        "profit_factor": 68.47,
        "net_profit": 68.47,
        "total_result_pct": 2.19,
        "avg_result_pct": 2.19,
        "winning_trades": 1,
        "losing_trades": 0,
        "avg_mfe_pct": 2.44,
        "avg_mae_pct": 0.19
      }
    ],
    "day_of_week_breakdown": [
      {
        "day_of_week": "Wednesday",
        "total_trades": 16,
        "win_rate": 37.5,
        "profit_factor": 0.46,
        "net_profit": -207.12,
        "total_result_pct": -5.78,
        "avg_result_pct": -0.36,
        "winning_trades": 6,
        "losing_trades": 10,
        "avg_mfe_pct": 0.8,
        "avg_mae_pct": 0.7
      },
      {
        "day_of_week": "Friday",
        "total_trades": 14,
        "win_rate": 28.57,
        "profit_factor": 0.6,
        "net_profit": -121.76,
        "total_result_pct": -4.52,
        "avg_result_pct": -0.32,
        "winning_trades": 4,
        "losing_trades": 10,
        "avg_mfe_pct": 0.73,
        "avg_mae_pct": 0.6
      },
      {
        "day_of_week": "Monday",
        "total_trades": 14,
        "win_rate": 21.43,
        "profit_factor": 0.36,
        "net_profit": -242.85,
        "total_result_pct": -4.76,
        "avg_result_pct": -0.34,
        "winning_trades": 3,
        "losing_trades": 11,
        "avg_mfe_pct": 0.73,
        "avg_mae_pct": 0.6
      },
      {
        "day_of_week": "Thursday",
        "total_trades": 14,
        "win_rate": 28.57,
        "profit_factor": 0.95,
        "net_profit": -13.6,
        "total_result_pct": -1.0,
        "avg_result_pct": -0.07,
        "winning_trades": 4,
        "losing_trades": 10,
        "avg_mfe_pct": 0.85,
        "avg_mae_pct": 0.56
      },
      {
        "day_of_week": "Tuesday",
        "total_trades": 14,
        "win_rate": 21.43,
        "profit_factor": 0.16,
        "net_profit": -357.35,
        "total_result_pct": -7.76,
        "avg_result_pct": -0.55,
        "winning_trades": 3,
        "losing_trades": 11,
        "avg_mfe_pct": 0.74,
        "avg_mae_pct": 0.58
      },
      {
        "day_of_week": "Saturday",
        "total_trades": 10,
        "win_rate": 50.0,
        "profit_factor": 0.98,
        "net_profit": -3.13,
        "total_result_pct": -0.67,
        "avg_result_pct": -0.07,
        "winning_trades": 5,
        "losing_trades": 5,
        "avg_mfe_pct": 0.89,
        "avg_mae_pct": 0.46
      },
      {
        "day_of_week": "Sunday",
        "total_trades": 10,
        "win_rate": 70.0,
        "profit_factor": 1.51,
        "net_profit": 75.27,
        "total_result_pct": 3.83,
        "avg_result_pct": 0.38,
        "winning_trades": 7,
        "losing_trades": 3,
        "avg_mfe_pct": 1.25,
        "avg_mae_pct": 0.57
      }
    ],
    "holding_time_breakdown": [
      {
        "holding_bucket": "4h-12h",
        "total_trades": 36,
        "win_rate": 27.78,
        "profit_factor": 0.55,
        "net_profit": -405.71,
        "total_result_pct": -9.49,
        "avg_result_pct": -0.26,
        "winning_trades": 10,
        "losing_trades": 26,
        "avg_mfe_pct": 0.78,
        "avg_mae_pct": 0.56
      },
      {
        "holding_bucket": ">12h",
        "total_trades": 31,
        "win_rate": 45.16,
        "profit_factor": 0.64,
        "net_profit": -192.13,
        "total_result_pct": -3.63,
        "avg_result_pct": -0.12,
        "winning_trades": 14,
        "losing_trades": 17,
        "avg_mfe_pct": 1.02,
        "avg_mae_pct": 0.59
      },
      {
        "holding_bucket": "1h-4h",
        "total_trades": 24,
        "win_rate": 33.33,
        "profit_factor": 0.62,
        "net_profit": -237.39,
        "total_result_pct": -6.33,
        "avg_result_pct": -0.26,
        "winning_trades": 8,
        "losing_trades": 16,
        "avg_mfe_pct": 0.72,
        "avg_mae_pct": 0.62
      },
      {
        "holding_bucket": "<=1h",
        "total_trades": 1,
        "win_rate": 0.0,
        "profit_factor": 0.0,
        "net_profit": -35.29,
        "total_result_pct": -1.2,
        "avg_result_pct": -1.2,
        "winning_trades": 0,
        "losing_trades": 1,
        "avg_mfe_pct": 0.0,
        "avg_mae_pct": 0.95
      }
    ],
    "equity_diagnostics": {
      "average_drawdown_pct": 8.31,
      "max_drawdown_pct": 10.13,
      "max_recovery_periods": 33922,
      "profit_giveback_pct": 649.64
    }
  },
  "candidate_count": 359,
  "approved_count": 359,
  "approval_rate_pct": 100.0,
  "signal_audit_summary": {
    "candidate_count": 0,
    "approved_count": 0,
    "blocked_count": 0,
    "approval_rate_pct": 0.0,
    "block_reason_counts": {},
    "approval_by_regime": {},
    "approval_by_market_state": {}
  }
}